atomic_hpc/__init__.py
atomic_hpc/config_yaml.py
atomic_hpc/deploy_runs.py
atomic_hpc/test_deploy_runs.py
atomic_hpc/test_read_config.py
atomic_hpc/test_utils.py
atomic_hpc/utils.py
atomic_hpc/context_folder/__init__.py
atomic_hpc/context_folder/abstract.py
atomic_hpc/context_folder/base.py
atomic_hpc/context_folder/local.py
atomic_hpc/context_folder/remote.py
atomic_hpc/context_folder/test_context_folder.py
atomic_hpc/frontend/__init__.py
atomic_hpc/frontend/retrieve_config.py
atomic_hpc/frontend/run_config.py
atomic_hpc/frontend/test_frontend.py
atomic_hpc/mockssh/__init__.py
atomic_hpc/mockssh/mockserver.py
atomic_hpc/mockssh/mocksftp.py
atomic_hpc/mockssh/test_mockssh.py
atomic_hpc-0.4.0.dist-info/LICENSE
atomic_hpc-0.4.0.dist-info/METADATA
atomic_hpc-0.4.0.dist-info/WHEEL
atomic_hpc-0.4.0.dist-info/entry_points.txt
atomic_hpc-0.4.0.dist-info/top_level.txt
atomic_hpc-0.4.0.dist-info/zip-safe
atomic_hpc-0.4.0.dist-info/RECORD
