Metadata-Version: 2.1
Name: atomic-hpc
Version: 0.4.0
Summary: A package for running multiple executable scripts on both local and remote hosts, configured using a YAML file
Home-page: https://github.com/chrisjsewell/atomic-hpc
Author: Chris Sewell
Author-email: chrisj_sewell@hotmail.com
License: MIT
Keywords: yaml,hpc,configuration,ssh,sftp
Platform: UNKNOWN
Classifier: Development Status :: 3 - Alpha
Classifier: Environment :: Console
Classifier: Environment :: Web Environment
Classifier: Intended Audience :: End Users/Desktop
Classifier: Intended Audience :: Science/Research
Classifier: License :: OSI Approved :: MIT License
Classifier: Operating System :: OS Independent
Classifier: Programming Language :: Python
Classifier: Programming Language :: Python :: 2
Classifier: Programming Language :: Python :: 2.7
Classifier: Programming Language :: Python :: 3
Classifier: Programming Language :: Python :: 3.2
Classifier: Programming Language :: Python :: 3.3
Classifier: Programming Language :: Python :: 3.4
Classifier: Programming Language :: Python :: 3.5
Classifier: Topic :: Scientific/Engineering :: Chemistry
Classifier: Topic :: Scientific/Engineering :: Physics
Classifier: Topic :: Software Development :: Libraries :: Python Modules
Classifier: Topic :: Utilities
Requires-Dist: ruamel.yaml (>=0.15.3)
Requires-Dist: jsonextended (>=0.5.6)
Requires-Dist: jsonschema
Requires-Dist: paramiko
